verifyml/LICENSE
verifyml/README.md
verifyml/WORKSPACE
verifyml/__init__.py
verifyml/setup.py
verifyml/.pytest_cache/.gitignore
verifyml/.pytest_cache/CACHEDIR.TAG
verifyml/.pytest_cache/README.md
verifyml/.pytest_cache/v/cache/nodeids
verifyml/.pytest_cache/v/cache/stepwise
verifyml/model_card_toolkit/BUILD
verifyml/model_card_toolkit/__init__.py
verifyml/model_card_toolkit/base_model_card_field.py
verifyml/model_card_toolkit/model_card.py
verifyml/model_card_toolkit/model_card_toolkit.py
verifyml/model_card_toolkit/move_generated_files.sh
verifyml/model_card_toolkit/version.py
verifyml/model_card_toolkit/.ipynb_checkpoints/model_card_toolkit-checkpoint.py
verifyml/model_card_toolkit/proto/BUILD
verifyml/model_card_toolkit/proto/gen_json_schema.sh
verifyml/model_card_toolkit/proto/model_card.proto
verifyml/model_card_toolkit/proto/model_card_pb2.py
verifyml/model_card_toolkit/schema/v0.0.1/model_card.schema.json
verifyml/model_card_toolkit/schema/v0.0.2/model_card.schema.json
verifyml/model_card_toolkit/schema/v0.0.3/model_card.schema.json
verifyml/model_card_toolkit/template/README.md
verifyml/model_card_toolkit/template/html/compare.html.jinja
verifyml/model_card_toolkit/template/html/default_template.html.jinja
verifyml/model_card_toolkit/template/md/default_template.md.jinja
verifyml/model_card_toolkit/utils/__init__.py
verifyml/model_card_toolkit/utils/json_util.py
verifyml/model_card_toolkit/utils/tally_form.py
verifyml/model_card_toolkit/utils/validation.py
verifyml/model_tests/DEVELOPMENT.ipynb
verifyml/model_tests/ModelTest.py
verifyml/model_tests/README.md
verifyml/model_tests/__init__.py
verifyml/model_tests/utils.py
verifyml/model_tests/FEAT/DataShift.py
verifyml/model_tests/FEAT/FeatureImportance.py
verifyml/model_tests/FEAT/MinMaxMetricThreshold.py
verifyml/model_tests/FEAT/Perturbation.py
verifyml/model_tests/FEAT/SHAPFeatureImportance.py
verifyml/model_tests/FEAT/SubgroupDisparity.py
verifyml/model_tests/FEAT/__init__.py
verifyml-0.0.6.dist-info/LICENSE
verifyml-0.0.6.dist-info/METADATA
verifyml-0.0.6.dist-info/WHEEL
verifyml-0.0.6.dist-info/top_level.txt
verifyml-0.0.6.dist-info/RECORD
