Metadata-Version: 2.1
Name: verifyml
Version: 0.0.6
Summary: An open-source toolkit to implement responsible AI workflows
Home-page: https://github.com/cylynx/verifyml
Author: Cylynx
Author-email: hello@cylynx.io
License: UNKNOWN
Project-URL: Bug Tracker, https://github.com/cylynx/verifyml/issues
Platform: UNKNOWN
Classifier: Programming Language :: Python :: 3
Classifier: License :: OSI Approved :: Apache Software License
Classifier: Operating System :: OS Independent
Requires-Python: >=3.8
License-File: LICENSE
Requires-Dist: absl-py (>=0.9)
Requires-Dist: semantic-version (>=2.8.0)
Requires-Dist: jinja2 (>=2.10)
Requires-Dist: matplotlib (>=3.2.0)
Requires-Dist: jsonschema (>=3.2.0)
Requires-Dist: scikit-learn (>=1.0)
Requires-Dist: category-encoders (>=2.2.2)
Requires-Dist: protobuf (>=3.18.0)
Requires-Dist: numpy (>=1.2)
Requires-Dist: numba (>=0.55.0)
Requires-Dist: pyparsing (<3.0.0a0,>=2.4.2)
Requires-Dist: shap (>=0.39.0)
Requires-Dist: scour (>=0.37)
